fastcube/__init__.py
fastcube/foo.py
fastcube-0.0.1.dist-info/LICENSE
fastcube-0.0.1.dist-info/METADATA
fastcube-0.0.1.dist-info/WHEEL
fastcube-0.0.1.dist-info/RECORD
