Metadata-Version: 2.1
Name: fastcube
Version: 0.0.1
Summary: This is a template repository for Python projects that use Poetry for their dependency management.
Home-page: https://github.com/csaybar/fastcube
Author: Cesar Aybar
Author-email: cesar.aybar@uv.es
Requires-Python: >=3.8,<4.0
Classifier: Programming Language :: Python :: 3
Classifier: Programming Language :: Python :: 3.8
Classifier: Programming Language :: Python :: 3.9
Classifier: Programming Language :: Python :: 3.10
Classifier: Programming Language :: Python :: 3.11
Classifier: Programming Language :: Python :: 3.12
Project-URL: Documentation, https://csaybar.github.io/fastcube/
Project-URL: Repository, https://github.com/csaybar/fastcube
